ysyx-workbench/预学习/Verilator_pre_exercise/on-off switch/npc/vsrc/onoff_switch.v
module onoff_switch(
  input a,
  input b,
  output f
);
  assign f = a ^ b;
endmodule

ysyx-workbench/npc/waveform.vcd
$version Generated by VerilatedVcd $end
$timescale 1ps $end

 $scope module TOP $end
  $var wire  1 # a $end
  $var wire  1 $ b $end
  $var wire  1 % f $end
  $scope module onoff_switch $end
   $var wire  1 # a $end
   $var wire  1 $ b $end
   $var wire  1 % f $end
  $upscope $end
 $upscope $end
$enddefinitions $end


#0
1#
0$
1%
#1
1$
0%
#2
#3
0#
0$
#4
1#
1$
#5
0#
1%
#6
#7
1#
0$
#8
0#
0%
#9
#10
1#
1%
#11
1$
0%
#12
0#
0$
#13
1$
1%
#14
1#
0%
#15
0$
1%
#16
0#
0%
#17
1#
1$
#18
0$
1%
#19
#20
1$
0%
#21
#22
0#
1%
#23
0$
0%
#24
1#
1%
#25
#26
#27
0#
1$
#28
0$
0%
#29
1$
1%
#30
1#
0%
#31
0#
1%
#32
#33
#34
1#
0%
#35
0#
1%
#36
#37
#38
0$
0%
#39
1#
1%
#40
#41
0#
0%
#42
#43
1#
1$
#44
0#
1%
#45
0$
0%
#46
#47
1#
1%
#48
0#
0%
#49
1$
1%
